meteva_base/__init__.py
meteva_base/basicdata/__init__.py
meteva_base/basicdata/check_out.py
meteva_base/basicdata/const.py
meteva_base/basicdata/ctl.py
meteva_base/basicdata/dicts.py
meteva_base/basicdata/grid.py
meteva_base/basicdata/grid_data.py
meteva_base/basicdata/keys_raw.py
meteva_base/basicdata/sta_data.py
meteva_base/basicdata/utils.py
meteva_base/fun/__init__.py
meteva_base/fun/combining.py
meteva_base/fun/computing.py
meteva_base/fun/diagnosing.py
meteva_base/fun/funs.py
meteva_base/fun/grouping.py
meteva_base/fun/interpolating.py
meteva_base/fun/nearing.py
meteva_base/fun/selecting.py
meteva_base/fun/statisticing.py
meteva_base/fun/timing.py
meteva_base/fun/transformating.py
meteva_base/function/__init__.py
meteva_base/function/get_from_grid_data.py
meteva_base/function/get_from_sta_data.py
meteva_base/function/gxy_gxy.py
meteva_base/function/gxy_gxym.py
meteva_base/function/gxy_sxy.py
meteva_base/function/gxym_gxy.py
meteva_base/function/gxym_gxym.py
meteva_base/function/put_into_grid_data.py
meteva_base/function/put_into_sta_data.py
meteva_base/function/sltdtxy_sltdtxym.py
meteva_base/function/sxy_gxy.py
meteva_base/function/sxy_gxym.py
meteva_base/function/sxy_sxy.py
meteva_base/function/sxy_sxym.py
meteva_base/function/sxym_sxy.py
meteva_base/io/CMADaasAccess.py
meteva_base/io/DataBlock_pb2.py
meteva_base/io/GDS_data_service.py
meteva_base/io/SignGenUtil.py
meteva_base/io/__init__.py
meteva_base/io/clienthandler.py
meteva_base/io/encoding.py
meteva_base/io/ftpconn.py
meteva_base/io/httpclient.py
meteva_base/io/httpconn.py
meteva_base/io/loglib.py
meteva_base/io/print_grib_info.py
meteva_base/io/read_graphydata.py
meteva_base/io/read_griddata.py
meteva_base/io/read_stadata.py
meteva_base/io/write_array.py
meteva_base/io/write_griddata.py
meteva_base/io/write_stadata.py
meteva_base/resources/colormaps/color_rain_1h.bak.txt
meteva_base/resources/colormaps/color_rain_1h.txt
meteva_base/resources/colormaps/color_rain_1h_error.txt
meteva_base-0.3.0.3.dist-info/LICENSE
meteva_base-0.3.0.3.dist-info/METADATA
meteva_base-0.3.0.3.dist-info/WHEEL
meteva_base-0.3.0.3.dist-info/top_level.txt
meteva_base-0.3.0.3.dist-info/RECORD
