Metadata-Version: 2.1
Name: meteva_base
Version: 0.3.0.3
Summary: base classes and functions of generally meteorogical usage, like Basic_class/IO/calculation/plot .etc
Home-page: https://github.com/guoyunqian/meteva_base
Author: NMC_WFT
Author-email: pangzide003@163.com
License: MIT
Classifier: Development Status :: 3 - Alpha
Classifier: Intended Audience :: Developers
Classifier: Programming Language :: Python :: 3
License-File: LICENSE
Requires-Dist: numpy >=2.0.2
Requires-Dist: h5py >=3.14.0
Requires-Dist: netCDF4 ==1.7.2
Requires-Dist: pyarrow >=21.0.0
Requires-Dist: pandas >=2.3.1
Requires-Dist: scipy >=1.13.0
Requires-Dist: xarray >=2024.7.0
Requires-Dist: scikit-learn >=1.5.0
Requires-Dist: matplotlib >=3.9.4
Requires-Dist: httplib2 >=0.12.0
Requires-Dist: protobuf <=3.20.3
Requires-Dist: tables >=3.4.4
Requires-Dist: urllib3 >=1.21.1
Requires-Dist: pyshp >=2.1.0
Requires-Dist: shapely >=1.8.0
Requires-Dist: ndindex >=1.10.1
